pyFAI/__init__.py
pyFAI/average.py
pyFAI/azimuthalIntegrator.py
pyFAI/blob_detection.py
pyFAI/calibrant.py
pyFAI/containers.py
pyFAI/control_points.py
pyFAI/diffmap.py
pyFAI/directories.py
pyFAI/distortion.py
pyFAI/geometryRefinement.py
pyFAI/goniometer.py
pyFAI/grid.py
pyFAI/load_integrators.py
pyFAI/massif.py
pyFAI/method_registry.py
pyFAI/multi_geometry.py
pyFAI/parallax.py
pyFAI/ring_extraction.py
pyFAI/spline.py
pyFAI/units.py
pyFAI/version.py
pyFAI/worker.py
pyFAI/app/__init__.py
pyFAI/app/average.py
pyFAI/app/benchmark.py
pyFAI/app/calib.py
pyFAI/app/calib2.py
pyFAI/app/check_calib.py
pyFAI/app/detector2nexus.py
pyFAI/app/diff_map.py
pyFAI/app/diff_tomo.py
pyFAI/app/drawmask.py
pyFAI/app/eiger_mask.py
pyFAI/app/integrate.py
pyFAI/app/mx_calibrate.py
pyFAI/app/peakfinder.py
pyFAI/app/pilx.py
pyFAI/app/recalib.py
pyFAI/app/saxs.py
pyFAI/app/sparsify.py
pyFAI/app/waxs.py
pyFAI/benchmark/__init__.py
pyFAI/crystallography/__init__.py
pyFAI/crystallography/calibrant.py
pyFAI/crystallography/calibrant_factory.py
pyFAI/crystallography/cell.py
pyFAI/crystallography/resolution.py
pyFAI/crystallography/space_groups.py
pyFAI/detectors/__init__.py
pyFAI/detectors/_adsc.py
pyFAI/detectors/_common.py
pyFAI/detectors/_dectris.py
pyFAI/detectors/_esrf.py
pyFAI/detectors/_hexagonal.py
pyFAI/detectors/_imxpad.py
pyFAI/detectors/_non_flat.py
pyFAI/detectors/_others.py
pyFAI/detectors/_psi.py
pyFAI/detectors/_rayonix.py
pyFAI/detectors/_xspectrum.py
pyFAI/detectors/orientation.py
pyFAI/detectors/sensors.py
pyFAI/engines/CSC_engine.py
pyFAI/engines/CSR_engine.py
pyFAI/engines/__init__.py
pyFAI/engines/histogram_engine.py
pyFAI/engines/preproc.py
pyFAI/ext/__init__.py
pyFAI/ext/_bispev.cpython-310-x86_64-linux-gnu.so
pyFAI/ext/_blob.cpython-310-x86_64-linux-gnu.so
pyFAI/ext/_convolution.cpython-310-x86_64-linux-gnu.so
pyFAI/ext/_distortion.cpython-310-x86_64-linux-gnu.so
pyfai-2025.12.1.dist-info/METADATA
pyfai-2025.12.1.dist-info/WHEEL
pyfai-2025.12.1.dist-info/copyright
pyfai-2025.12.1.dist-info/entry_points.txt
pyfai-2025.12.1.dist-info/RECORD
pyfai-2025.12.1.dist-info/sboms/auditwheel.cdx.json
