Metadata-Version: 2.1
Name: pyFAI
Version: 2025.12.1
Summary: Python implementation of fast azimuthal integration
Author: Gael Goret, Brian Pauw
Author-Email: =?utf-8?q?J=C3=A9r=C3=B4me_Kieffer?= <jerome.kieffer@esrf.fr>, Edgar Gutierrez Fernandez <edgar.gutierrez-fernandez@esrf.fr>, Valentin Valls <valentin.valls@esrf.fr>, =?utf-8?q?Lo=C3=AFc_Huder?= <loic.huder@esrf.fr>, "Jonathan P. Wright" <wright@esrf.fr>
License: Format: http://www.debian.org/doc/packaging-manuals/copyright-format/1.0/
Classifier: Development Status :: 5 - Production/Stable
Classifier: Intended Audience :: Developers
Classifier: Programming Language :: Python :: 3
Classifier: Programming Language :: Python :: 3.10
Classifier: Programming Language :: Python :: 3.11
Classifier: Programming Language :: Python :: 3.12
Classifier: Programming Language :: Python :: 3.13
Classifier: Programming Language :: Python :: 3.14
Classifier: Programming Language :: Python :: Implementation :: CPython
Classifier: Programming Language :: Cython
Classifier: Environment :: Console
Classifier: Environment :: X11 Applications :: Qt
Classifier: Intended Audience :: Science/Research
Classifier: License :: OSI Approved :: MIT License
Classifier: Topic :: Software Development :: Libraries :: Python Modules
Classifier: Operating System :: Microsoft :: Windows
Classifier: Operating System :: Unix
Classifier: Operating System :: MacOS :: MacOS X
Classifier: Operating System :: POSIX
Classifier: Topic :: Scientific/Engineering :: Physics
Project-URL: homepage, http://www.silx.org
Project-URL: documentation, http://www.silx.org/doc/pyFAI/latest/
Project-URL: source, https://github.com/silx-kit/pyFAI
Project-URL: download, https://github.com/silx-kit/pyFAI/releases
Project-URL: tracker, https://github.com/silx-kit/pyFAI/issues
Requires-Python: >=3.10
Requires-Dist: numpy>=1.10
Requires-Dist: h5py
Requires-Dist: fabio
Requires-Dist: silx>=2
Requires-Dist: numexpr!=2.8.6
Requires-Dist: scipy
Requires-Dist: matplotlib
Provides-Extra: gui
Requires-Dist: PySide6; extra == "gui"
Provides-Extra: opencl
Requires-Dist: pyopencl; extra == "opencl"
Provides-Extra: all
Requires-Dist: PySide6; extra == "all"
Requires-Dist: pyopencl; extra == "all"
Requires-Dist: hdf5plugin; extra == "all"
